<Page loaded="pageLoaded" unloaded="pageUnloaded" navigatingTo="navigatingTo"
  actionBarHidden="true" xmlns:VideoPlayer="nativescript-videoplayer">
		<StackLayout>
        <Label text=" How to Enable Services" textWrap='true' class="title"/>
        <StackLayout>
          <ScrollView height="80%">
            <StackLayout >
              <Label textWrap="true" text="Ok. We promise this is the last time we will need to ask you for enabling permissions."></Label>
              <Label textWrap="true" text="The Accessibility permission allows us to sense which app you are using so we can give you an appropriate nudge if you asked for it."></Label>
              <Label textWrap="true" text="1. Tap the button below to get to your Settings." class="information"/>
              <Label textWrap="true" text="2. Once there, tap on 'HabitLab' to get to HabitLab's service page." class="information"/>
              <Image src="~/images/accessibility_example.jpg" class="information-image" />
              <Label textWrap="true" text="3. Tap on the toggle to switch it to the 'on' position!" class="information"/>
              <Label textWrap="true" text="4. If your Android version is less than 6.0, restart your phone." class="information"/>
              <Label textWrap="true" text="5. Start the app again." class="information"/>
            </StackLayout>
          </ScrollView>
        <Button id="accessibilityButton" text="Give Accessibility Permission" tap="giveAccessibilityPermission"/>
      </StackLayout>
    </StackLayout>
</Page>
